{
  "schema_version": 1,
  "asset_id": "ansimuz_sci_fi_ramp_with_light_af2e6e81_tile_118",
  "asset_name": "Sci Fi Ramp With Light Tile 118",
  "category": "terrain",
  "runtime_template": "terrain",
  "visual": "ansimuz_sci_fi_ramp_with_light_af2e6e81_tile_118.png",
  "visual_tags": [
    "ansimuz",
    "sci",
    "fi",
    "ramp",
    "with",
    "light",
    "af2e6e81",
    "tiles",
    "and",
    "terrain",
    "legacy",
    "collection",
    "assets",
    "warped",
    "environments",
    "bulkhead",
    "walls",
    "v2",
    "png",
    "tile",
    "slice"
  ],
  "source_pack": "ansimuz",
  "source_author": "ansimuz",
  "source_collection": "ansimuz",
  "is_spritesheet": false,
  "is_uniform_grid": false,
  "grid_cell_size": null,
  "slicing_confidence": 1.0,
  "frames": [
    {
      "x": 0,
      "y": 0,
      "w": 16,
      "h": 16
    }
  ],
  "placement_logic": {
    "snapping_type": "edge_to_edge",
    "parallax_bucket": "play_layer"
  },
  "collision": {
    "shape": "rectangle",
    "size": [
      16,
      16
    ]
  }
}