{
  "schema_version": 1,
  "asset_id": "ansimuz_pixel_art_rocky_terrain_tile_223073cf_tile_264",
  "asset_name": "Pixel Art Rocky Terrain Tile Tile 264",
  "category": "terrain",
  "runtime_template": "terrain",
  "visual": "ansimuz_pixel_art_rocky_terrain_tile_223073cf_tile_264.png",
  "visual_tags": [
    "ansimuz",
    "pixel",
    "art",
    "rocky",
    "terrain",
    "tile",
    "223073cf",
    "tiles",
    "and",
    "legacy",
    "collection",
    "assets",
    "gothicvania",
    "environments",
    "pass",
    "files",
    "png",
    "tile",
    "slice"
  ],
  "source_pack": "ansimuz",
  "source_author": "ansimuz",
  "source_collection": "ansimuz",
  "is_spritesheet": false,
  "is_uniform_grid": false,
  "grid_cell_size": null,
  "slicing_confidence": 1.0,
  "frames": [
    {
      "x": 0,
      "y": 0,
      "w": 16,
      "h": 16
    }
  ],
  "placement_logic": {
    "snapping_type": "edge_to_edge",
    "parallax_bucket": "play_layer"
  },
  "collision": {
    "shape": "rectangle",
    "size": [
      16,
      16
    ]
  }
}